{"chunk_definitions":[{"row":53,"row_count":1,"visible":true,"expansion_state":0,"options":{"engine":"r","label":"setup","include":false,"dev":"png"},"document_id":"9051B597","chunk_id":"csetup_chunk","chunk_label":"setup"},{"row":82,"row_count":1,"visible":true,"expansion_state":0,"options":{"engine":"r","message":false,"label":"unnamed-chunk-27","dev":"png"},"document_id":"9051B597","chunk_id":"cp79pwsdxccbg","chunk_label":"unnamed-chunk-2"},{"row":102,"row_count":1,"visible":true,"expansion_state":0,"options":{"engine":"r","label":"unnamed-chunk-14","dev":"png"},"document_id":"9051B597","chunk_id":"ckp5fj8o1xccx","chunk_label":"unnamed-chunk-3"},{"row":116,"row_count":1,"visible":true,"expansion_state":0,"options":{"engine":"r","label":"unnamed-chunk-5","dev":"png"},"document_id":"9051B597","chunk_id":"ceq3bkvpalwkr","chunk_label":"unnamed-chunk-4"},{"row":154,"row_count":1,"visible":true,"expansion_state":0,"options":{"engine":"r","label":"unnamed-chunk-4","dev":"png"},"document_id":"9051B597","chunk_id":"cfzwv1vs4eqdq","chunk_label":"unnamed-chunk-6"},{"row":166,"row_count":1,"visible":true,"expansion_state":0,"options":{"engine":"r","label":"unnamed-chunk-8","dev":"png"},"document_id":"9051B597","chunk_id":"cajl56dy6ha8i","chunk_label":"unnamed-chunk-7"},{"row":173,"row_count":1,"visible":true,"expansion_state":0,"options":{"engine":"r","label":"unnamed-chunk-9","dev":"png"},"document_id":"9051B597","chunk_id":"c7ujilz4tckh2","chunk_label":"unnamed-chunk-8"},{"row":189,"row_count":1,"visible":true,"expansion_state":0,"options":{"engine":"r","label":"unnamed-chunk-12","dev":"png"},"document_id":"9051B597","chunk_id":"ca7ek3w78883g","chunk_label":"unnamed-chunk-9"},{"row":203,"row_count":1,"visible":true,"expansion_state":0,"options":{"engine":"r","label":"unnamed-chunk-17","dev":"png"},"document_id":"9051B597","chunk_id":"cd3b6ib5208jl","chunk_label":"unnamed-chunk-10"},{"row":225,"row_count":1,"visible":true,"expansion_state":0,"options":{"engine":"r","label":"unnamed-chunk-18","dev":"png"},"document_id":"9051B597","chunk_id":"cpw7ip4fq76jw","chunk_label":"unnamed-chunk-11"},{"row":253,"row_count":1,"visible":true,"expansion_state":0,"options":{"engine":"r","label":"unnamed-chunk-20","dev":"png"},"document_id":"9051B597","chunk_id":"c5ge03o09fuvt","chunk_label":"unnamed-chunk-12"},{"row":292,"row_count":1,"visible":true,"expansion_state":0,"options":{"engine":"r","label":"unnamed-chunk-24","dev":"png"},"document_id":"9051B597","chunk_id":"c5df7ln901a3s","chunk_label":"unnamed-chunk-13"},{"row":308,"row_count":1,"visible":true,"expansion_state":0,"options":{"engine":"r","label":"unnamed-chunk-26","dev":"png"},"document_id":"9051B597","chunk_id":"cdn4cfhrilscb","chunk_label":"unnamed-chunk-14"},{"row":346,"row_count":1,"visible":true,"expansion_state":0,"options":{"engine":"r","label":"unnamed-chunk-15","dev":"png"},"document_id":"9051B597","chunk_id":"c7vzan9y8g91u","chunk_label":"unnamed-chunk-15"},{"row":373,"row_count":1,"visible":true,"expansion_state":0,"options":{"engine":"r","label":"unnamed-chunk-20","dev":"png"},"document_id":"BFC83BCC","chunk_id":"c5vivn0b8sqaz","chunk_label":"unnamed-chunk-16"}],"doc_write_time":1722867744,"chunk_rendered_width":597,"working_dir":null,"default_chunk_options":{"echo":true,"warning":false}}